GonulluGUI-1.0.data/scripts/gonullu-gui
GonulluGUI-1.0.data/scripts/gonullu-gui-main
GonulluGUI-1.0.dist-info/DESCRIPTION.rst
GonulluGUI-1.0.dist-info/METADATA
GonulluGUI-1.0.dist-info/RECORD
GonulluGUI-1.0.dist-info/WHEEL
GonulluGUI-1.0.dist-info/metadata.json
GonulluGUI-1.0.dist-info/top_level.txt
gonullugui/__init__.py
gonullugui/coreui.py
gonullugui/version.py
usr/local/share/gonullu-gui/langs/en_US.qm
usr/local/share/gonullu-gui/langs/tr_TR.qm
usr/share/applications/gonullu-gui.desktop
usr/share/polkit-1/actions/org.freedesktop.policykit.gonullu-gui-local.policy
usr/share/polkit-1/actions/org.freedesktop.policykit.gonullu-gui.policy
