Metadata-Version: 2.0
Name: GonulluGUI
Version: 1.0
Summary: Graphical user interface for Gonullu.
Home-page: https://github.com/eersoy93/gonullu-gui
Author: Erdem Ersoy
Author-email: erdemersoy@live.com
License: GPLv3
Keywords: PyQt5,gonullu
Platform: UNKNOWN
